stdio_socket/__init__.py
stdio_socket/__main__.py
stdio_socket/_version.py
stdio_socket/console.py
stdio_socket/expose.py
stdio_socket/psuedo_tty.py
stdio_socket/version.py
stdio_socket-1.4.0.dist-info/licenses/LICENSE
stdio_socket-1.4.0.dist-info/METADATA
stdio_socket-1.4.0.dist-info/WHEEL
stdio_socket-1.4.0.dist-info/entry_points.txt
stdio_socket-1.4.0.dist-info/top_level.txt
stdio_socket-1.4.0.dist-info/RECORD
